win_cmd_escaper.py
win_cmd_escaper-1.0.0.dist-info/LICENSE
win_cmd_escaper-1.0.0.dist-info/METADATA
win_cmd_escaper-1.0.0.dist-info/WHEEL
win_cmd_escaper-1.0.0.dist-info/top_level.txt
win_cmd_escaper-1.0.0.dist-info/RECORD
