Metadata-Version: 2.1
Name: win-cmd-escaper
Version: 1.0.0
Summary: A Python library to properly handle escaping of command line arguments in Windows' CMD.exe and Powershell.
Home-page: https://github.com/nicolas-van/win-cmd-escaper
Author: Nicolas Vanhoren
License: MIT
Project-URL: Bug Reports, https://github.com/nicolas-van/win-cmd-escaper/issues
Project-URL: Source, https://github.com/nicolas-van/win-cmd-escaper
Keywords: windows cmd powershell
Classifier: Development Status :: 5 - Production/Stable
Classifier: Environment :: Console
Classifier: Intended Audience :: System Administrators
Classifier: Operating System :: OS Independent
Classifier: Topic :: System :: Systems Administration
Classifier: License :: OSI Approved :: MIT License
Classifier: Programming Language :: Python :: 3
Classifier: Programming Language :: Python :: 3.6
Classifier: Programming Language :: Python :: 3.7
Classifier: Programming Language :: Python :: 3.8
Classifier: Programming Language :: Python :: 3.9
Classifier: Programming Language :: Python :: 3.10
Classifier: Programming Language :: Python :: 3.11
Requires-Python: >=3.6
License-File: LICENSE
